{
  "TIT2641": {
    "type": "SIGNAL",
    "cx": 339.5,
    "cy": 220.3,
    "x1": 293.0,
    "y1": 206.4,
    "x2": 386.0,
    "y2": 234.3,
    "ports": [
      {
        "name": "A",
        "type": "PORT",
        "cx": 320.4,
        "cy": 258.2
      },
      {
        "name": "G",
        "type": "PORT",
        "cx": 360.1,
        "cy": 258.2
      }
    ]
  },
  "D03-524-01": {
    "type": "REF_SIGNAL",
    "cx": 577.0,
    "cy": 220.3,
    "x1": 511.0,
    "y1": 206.4,
    "x2": 643.0,
    "y2": 234.3,
    "ports": [
      {
        "name": "G",
        "type": "PORT",
        "cx": 600.1,
        "cy": 258.2
      },
      {
        "name": "3/524",
        "type": "SHEET_REF",
        "cx": 634.4,
        "cy": 382.5
      }
    ]
  },
  "D03-526-04": {
    "type": "REF_SIGNAL",
    "cx": 955.0,
    "cy": 220.3,
    "x1": 889.0,
    "y1": 206.4,
    "x2": 1021.0,
    "y2": 234.3,
    "ports": [
      {
        "name": "G",
        "type": "PORT",
        "cx": 980.1,
        "cy": 258.2
      },
      {
        "name": "3/526",
        "type": "SHEET_REF",
        "cx": 1014.4,
        "cy": 382.5
      }
    ]
  },
  "PIT2621": {
    "type": "SIGNAL",
    "cx": 4659.2,
    "cy": 220.3,
    "x1": 4612.0,
    "y1": 206.4,
    "x2": 4706.4,
    "y2": 234.3,
    "ports": [
      {
        "name": "A",
        "type": "PORT",
        "cx": 4640.4,
        "cy": 258.2
      },
      {
        "name": "G",
        "type": "PORT",
        "cx": 4680.1,
        "cy": 258.2
      }
    ]
  },
  "PIT2626": {
    "type": "SIGNAL",
    "cx": 5017.2,
    "cy": 220.3,
    "x1": 4970.0,
    "y1": 206.4,
    "x2": 5064.4,
    "y2": 234.3,
    "ports": [
      {
        "name": "A",
        "type": "PORT",
        "cx": 5000.4,
        "cy": 258.2
      },
      {
        "name": "G",
        "type": "PORT",
        "cx": 5040.1,
        "cy": 258.2
      }
    ]
  },
  "OCB0088009": {
    "type": "OCB_BLOCK",
    "cx": 3105.7,
    "cy": 470.3,
    "x1": 3030.0,
    "y1": 456.4,
    "x2": 3181.4,
    "y2": 484.3,
    "ports": [
      {
        "name": "A",
        "type": "PORT",
        "cx": 2979.7,
        "cy": 425.6
      },
      {
        "name": "OUT",
        "type": "PORT",
        "cx": 3039.8,
        "cy": 430.8
      }
    ]
  },
  "IN1": {
    "type": "SIGNAL",
    "cx": 4650.8,
    "cy": 2932.3,
    "x1": 4642.4,
    "y1": 2920.7,
    "x2": 4659.2,
    "y2": 2944.0,
    "ports": [
      {
        "name": "OUT",
        "type": "PORT",
        "cx": 3039.8,
        "cy": 610.8
      },
      {
        "name": "OUT",
        "type": "PORT",
        "cx": 4670.8,
        "cy": 644.2
      },
      {
        "name": "ABS",
        "type": "BLOCK_TYPE",
        "cx": 4679.0,
        "cy": 764.3
      },
      {
        "name": "OUT",
        "type": "PORT",
        "cx": 4670.8,
        "cy": 824.2
      },
      {
        "name": "H",
        "type": "BLOCK_TYPE",
        "cx": 4997.0,
        "cy": 1274.3
      },
      {
        "name": "OUT",
        "type": "PORT",
        "cx": 5010.8,
        "cy": 1324.2
      },
      {
        "name": "OUT",
        "type": "PORT",
        "cx": 4539.8,
        "cy": 1370.8
      },
      {
        "name": "OUT",
        "type": "PORT",
        "cx": 4650.8,
        "cy": 2164.2
      },
      {
        "name": "OUT",
        "type": "PORT",
        "cx": 1839.8,
        "cy": 2190.8
      },
      {
        "name": "N",
        "type": "BLOCK_TYPE",
        "cx": 1801.3,
        "cy": 2193.2
      },
      {
        "name": "OUT",
        "type": "PORT",
        "cx": 879.8,
        "cy": 2230.8
      },
      {
        "name": "OUT",
        "type": "PORT",
        "cx": 3259.8,
        "cy": 2230.8
      },
      {
        "name": "N",
        "type": "BLOCK_TYPE",
        "cx": 841.3,
        "cy": 2233.2
      },
      {
        "name": "N",
        "type": "BLOCK_TYPE",
        "cx": 3221.3,
        "cy": 2233.2
      },
      {
        "name": "N",
        "type": "BLOCK_TYPE",
        "cx": 4741.3,
        "cy": 2233.2
      },
      {
        "name": "OUT",
        "type": "PORT",
        "cx": 1179.8,
        "cy": 2270.8
      },
      {
        "name": "OUT",
        "type": "PORT",
        "cx": 3559.8,
        "cy": 2270.8
      },
      {
        "name": "OUT",
        "type": "PORT",
        "cx": 4999.8,
        "cy": 2270.8
      },
      {
        "name": "T",
        "type": "BLOCK_TYPE",
        "cx": 940.4,
        "cy": 2472.0
      },
      {
        "name": "A",
        "type": "PORT",
        "cx": 1019.5,
        "cy": 2472.0
      },
      {
        "name": "T",
        "type": "BLOCK_TYPE",
        "cx": 1960.4,
        "cy": 2472.0
      },
      {
        "name": "A",
        "type": "PORT",
        "cx": 2039.5,
        "cy": 2472.0
      },
      {
        "name": "T",
        "type": "BLOCK_TYPE",
        "cx": 3320.4,
        "cy": 2472.0
      },
      {
        "name": "A",
        "type": "PORT",
        "cx": 3399.5,
        "cy": 2472.0
      },
      {
        "name": "T",
        "type": "BLOCK_TYPE",
        "cx": 4660.4,
        "cy": 2472.0
      },
      {
        "name": "A",
        "type": "PORT",
        "cx": 4739.5,
        "cy": 2472.0
      }
    ]
  },
  "IN2": {
    "type": "SIGNAL",
    "cx": 4873.7,
    "cy": 2310.8,
    "x1": 4862.0,
    "y1": 2302.4,
    "x2": 4885.3,
    "y2": 2319.2,
    "ports": [
      {
        "name": "OR",
        "type": "BLOCK_TYPE",
        "cx": 2979.7,
        "cy": 614.3
      },
      {
        "name": "OR",
        "type": "BLOCK_TYPE",
        "cx": 4479.7,
        "cy": 1374.3
      },
      {
        "name": "AND",
        "type": "BLOCK_TYPE",
        "cx": 1118.4,
        "cy": 2274.3
      },
      {
        "name": "AND",
        "type": "BLOCK_TYPE",
        "cx": 3498.4,
        "cy": 2274.3
      },
      {
        "name": "AND",
        "type": "BLOCK_TYPE",
        "cx": 4938.4,
        "cy": 2274.3
      }
    ]
  },
  "D03-068-02": {
    "type": "REF_SIGNAL",
    "cx": 2719.0,
    "cy": 568.3,
    "x1": 2653.0,
    "y1": 554.4,
    "x2": 2785.0,
    "y2": 582.3,
    "ports": [
      {
        "name": "3/068",
        "type": "SHEET_REF",
        "cx": 2644.4,
        "cy": 612.5
      }
    ]
  },
  "OCB0088007": {
    "type": "OCB_BLOCK",
    "cx": 445.7,
    "cy": 604.3,
    "x1": 370.0,
    "y1": 590.4,
    "x2": 521.4,
    "y2": 618.3,
    "ports": [
      {
        "name": "NUM",
        "type": "PORT",
        "cx": 330.8,
        "cy": 486.9
      },
      {
        "name": "DEN",
        "type": "PORT",
        "cx": 370.8,
        "cy": 488.2
      },
      {
        "name": "OUT",
        "type": "PORT",
        "cx": 350.8,
        "cy": 604.2
      }
    ]
  },
  "OCB0088016": {
    "type": "OCB_BLOCK",
    "cx": 4765.7,
    "cy": 643.3,
    "x1": 4690.0,
    "y1": 629.4,
    "x2": 4841.4,
    "y2": 657.3,
    "ports": []
  },
  "D03-066-02": {
    "type": "REF_SIGNAL",
    "cx": 2719.0,
    "cy": 688.3,
    "x1": 2653.0,
    "y1": 674.4,
    "x2": 2785.0,
    "y2": 702.3,
    "ports": [
      {
        "name": "3/066",
        "type": "SHEET_REF",
        "cx": 2644.4,
        "cy": 732.5
      }
    ]
  },
  "OCB008802C": {
    "type": "OCB_BLOCK",
    "cx": 3427.8,
    "cy": 918.3,
    "x1": 3350.0,
    "y1": 904.4,
    "x2": 3505.6,
    "y2": 932.3,
    "ports": [
      {
        "name": "FLAG",
        "type": "PORT",
        "cx": 3281.5,
        "cy": 789.2
      },
      {
        "name": "NO",
        "type": "PORT",
        "cx": 3330.8,
        "cy": 792.8
      },
      {
        "name": "YES",
        "type": "PORT",
        "cx": 3269.0,
        "cy": 850.8
      },
      {
        "name": "T",
        "type": "BLOCK_TYPE",
        "cx": 3340.4,
        "cy": 854.0
      },
      {
        "name": "OUT",
        "type": "PORT",
        "cx": 3330.8,
        "cy": 924.2
      }
    ]
  },
  "OCB0088014": {
    "type": "OCB_BLOCK",
    "cx": 4385.7,
    "cy": 990.3,
    "x1": 4310.0,
    "y1": 976.4,
    "x2": 4461.4,
    "y2": 1004.3,
    "ports": [
      {
        "name": "A",
        "type": "PORT",
        "cx": 4259.6,
        "cy": 945.6
      },
      {
        "name": "OUT",
        "type": "PORT",
        "cx": 4319.8,
        "cy": 950.8
      }
    ]
  },
  "ALG-0113015": {
    "type": "ALG_BLOCK",
    "cx": 4831.8,
    "cy": 1075.3,
    "x1": 4754.0,
    "y1": 1061.4,
    "x2": 4909.6,
    "y2": 1089.3,
    "ports": [
      {
        "name": "A",
        "type": "PORT",
        "cx": 4919.5,
        "cy": 972.0
      },
      {
        "name": "OUT",
        "type": "PORT",
        "cx": 4910.8,
        "cy": 1044.2
      }
    ]
  },
  "D03-062-01": {
    "type": "REF_SIGNAL",
    "cx": 659.0,
    "cy": 1088.3,
    "x1": 593.0,
    "y1": 1074.4,
    "x2": 725.0,
    "y2": 1102.3,
    "ports": [
      {
        "name": "3/062",
        "type": "SHEET_REF",
        "cx": 584.4,
        "cy": 1132.5
      }
    ]
  },
  "D03-062-02": {
    "type": "REF_SIGNAL",
    "cx": 1699.0,
    "cy": 1088.3,
    "x1": 1633.0,
    "y1": 1074.4,
    "x2": 1765.0,
    "y2": 1102.3,
    "ports": [
      {
        "name": "3/062",
        "type": "SHEET_REF",
        "cx": 1624.4,
        "cy": 1132.5
      }
    ]
  },
  "D03-062-03": {
    "type": "REF_SIGNAL",
    "cx": 2719.0,
    "cy": 1088.3,
    "x1": 2653.0,
    "y1": 1074.4,
    "x2": 2785.0,
    "y2": 1102.3,
    "ports": [
      {
        "name": "3/062",
        "type": "SHEET_REF",
        "cx": 2644.4,
        "cy": 1132.5
      }
    ]
  },
  "D03-066-01": {
    "type": "REF_SIGNAL",
    "cx": 4079.0,
    "cy": 1088.3,
    "x1": 4013.0,
    "y1": 1074.4,
    "x2": 4145.0,
    "y2": 1102.3,
    "ports": [
      {
        "name": "3/066",
        "type": "SHEET_REF",
        "cx": 4004.4,
        "cy": 1132.5
      }
    ]
  },
  "IN3": {
    "type": "SIGNAL",
    "cx": 2113.7,
    "cy": 2270.8,
    "x1": 2102.0,
    "y1": 2262.4,
    "x2": 2125.3,
    "y2": 2279.2,
    "ports": [
      {
        "name": "OUT",
        "type": "PORT",
        "cx": 4439.8,
        "cy": 1130.8
      },
      {
        "name": "OR",
        "type": "BLOCK_TYPE",
        "cx": 4379.7,
        "cy": 1134.3
      },
      {
        "name": "OUT",
        "type": "PORT",
        "cx": 2239.8,
        "cy": 2270.8
      },
      {
        "name": "AND",
        "type": "BLOCK_TYPE",
        "cx": 2178.4,
        "cy": 2274.3
      }
    ]
  },
  "D03-511-12": {
    "type": "REF_SIGNAL",
    "cx": 4079.0,
    "cy": 1188.3,
    "x1": 4013.0,
    "y1": 1174.4,
    "x2": 4145.0,
    "y2": 1202.3,
    "ports": [
      {
        "name": "3/511",
        "type": "SHEET_REF",
        "cx": 4004.4,
        "cy": 1232.5
      }
    ]
  },
  "OCB0088043": {
    "type": "OCB_BLOCK",
    "cx": 4765.7,
    "cy": 1278.3,
    "x1": 4690.0,
    "y1": 1264.4,
    "x2": 4841.4,
    "y2": 1292.3,
    "ports": [
      {
        "name": "FLAG",
        "type": "PORT",
        "cx": 4621.5,
        "cy": 1149.2
      },
      {
        "name": "NO",
        "type": "PORT",
        "cx": 4670.8,
        "cy": 1152.8
      },
      {
        "name": "YES",
        "type": "PORT",
        "cx": 4609.0,
        "cy": 1210.8
      },
      {
        "name": "T",
        "type": "BLOCK_TYPE",
        "cx": 4680.4,
        "cy": 1214.0
      },
      {
        "name": "OUT",
        "type": "PORT",
        "cx": 4670.8,
        "cy": 1284.2
      }
    ]
  },
  "OCB008800D": {
    "type": "OCB_BLOCK",
    "cx": 627.8,
    "cy": 1290.3,
    "x1": 550.0,
    "y1": 1276.4,
    "x2": 705.6,
    "y2": 1304.3,
    "ports": [
      {
        "name": "A",
        "type": "PORT",
        "cx": 499.6,
        "cy": 1245.7
      },
      {
        "name": "OUT",
        "type": "PORT",
        "cx": 559.8,
        "cy": 1250.8
      }
    ]
  },
  "OCB008801C": {
    "type": "OCB_BLOCK",
    "cx": 1667.8,
    "cy": 1290.3,
    "x1": 1590.0,
    "y1": 1276.4,
    "x2": 1745.6,
    "y2": 1304.3,
    "ports": [
      {
        "name": "A",
        "type": "PORT",
        "cx": 1539.7,
        "cy": 1245.7
      },
      {
        "name": "OUT",
        "type": "PORT",
        "cx": 1599.8,
        "cy": 1250.8
      }
    ]
  },
  "OCB008802A": {
    "type": "OCB_BLOCK",
    "cx": 2687.1,
    "cy": 1290.3,
    "x1": 2610.0,
    "y1": 1276.4,
    "x2": 2764.2,
    "y2": 1304.3,
    "ports": [
      {
        "name": "A",
        "type": "PORT",
        "cx": 2559.7,
        "cy": 1245.7
      },
      {
        "name": "OUT",
        "type": "PORT",
        "cx": 2619.8,
        "cy": 1250.8
      }
    ]
  },
  "OCB0088005": {
    "type": "OCB_BLOCK",
    "cx": 3425.7,
    "cy": 1318.3,
    "x1": 3350.0,
    "y1": 1304.4,
    "x2": 3501.4,
    "y2": 1332.3,
    "ports": [
      {
        "name": "FLAG",
        "type": "PORT",
        "cx": 3281.5,
        "cy": 1189.2
      },
      {
        "name": "NO",
        "type": "PORT",
        "cx": 3330.8,
        "cy": 1192.8
      },
      {
        "name": "YES",
        "type": "PORT",
        "cx": 3269.0,
        "cy": 1250.8
      },
      {
        "name": "T",
        "type": "BLOCK_TYPE",
        "cx": 3340.4,
        "cy": 1254.0
      },
      {
        "name": "OUT",
        "type": "PORT",
        "cx": 3330.8,
        "cy": 1324.2
      }
    ]
  },
  "OCB0088008": {
    "type": "OCB_BLOCK",
    "cx": 1045.7,
    "cy": 1320.3,
    "x1": 970.0,
    "y1": 1306.4,
    "x2": 1121.4,
    "y2": 1334.3,
    "ports": [
      {
        "name": "YES",
        "type": "PORT",
        "cx": 950.8,
        "cy": 1189.0
      },
      {
        "name": "FLAG",
        "type": "PORT",
        "cx": 901.5,
        "cy": 1189.2
      },
      {
        "name": "NO",
        "type": "PORT",
        "cx": 893.2,
        "cy": 1250.8
      },
      {
        "name": "T",
        "type": "BLOCK_TYPE",
        "cx": 960.4,
        "cy": 1254.0
      },
      {
        "name": "OUT",
        "type": "PORT",
        "cx": 950.8,
        "cy": 1324.2
      }
    ]
  },
  "OCB008801A": {
    "type": "OCB_BLOCK",
    "cx": 2067.1,
    "cy": 1320.3,
    "x1": 1990.0,
    "y1": 1306.4,
    "x2": 2144.2,
    "y2": 1334.3,
    "ports": [
      {
        "name": "YES",
        "type": "PORT",
        "cx": 1970.8,
        "cy": 1189.0
      },
      {
        "name": "FLAG",
        "type": "PORT",
        "cx": 1921.5,
        "cy": 1189.2
      },
      {
        "name": "NO",
        "type": "PORT",
        "cx": 1913.2,
        "cy": 1250.8
      },
      {
        "name": "T",
        "type": "BLOCK_TYPE",
        "cx": 1980.4,
        "cy": 1254.0
      },
      {
        "name": "OUT",
        "type": "PORT",
        "cx": 1970.8,
        "cy": 1324.2
      }
    ]
  },
  "OCB008804E": {
    "type": "OCB_BLOCK",
    "cx": 5107.1,
    "cy": 1325.3,
    "x1": 5030.0,
    "y1": 1311.4,
    "x2": 5184.2,
    "y2": 1339.3,
    "ports": []
  },
  "D03-064-01": {
    "type": "REF_SIGNAL",
    "cx": 4079.0,
    "cy": 1328.3,
    "x1": 4013.0,
    "y1": 1314.4,
    "x2": 4145.0,
    "y2": 1342.3,
    "ports": [
      {
        "name": "3/064",
        "type": "SHEET_REF",
        "cx": 4004.4,
        "cy": 1372.5
      }
    ]
  },
  "D03-522-02": {
    "type": "REF_SIGNAL",
    "cx": 659.0,
    "cy": 1408.3,
    "x1": 593.0,
    "y1": 1394.4,
    "x2": 725.0,
    "y2": 1422.3,
    "ports": [
      {
        "name": "3/522",
        "type": "SHEET_REF",
        "cx": 584.4,
        "cy": 1452.5
      }
    ]
  },
  "D03-068-01": {
    "type": "REF_SIGNAL",
    "cx": 4079.0,
    "cy": 1468.3,
    "x1": 4013.0,
    "y1": 1454.4,
    "x2": 4145.0,
    "y2": 1482.3,
    "ports": [
      {
        "name": "3/068",
        "type": "SHEET_REF",
        "cx": 4004.4,
        "cy": 1472.5
      }
    ]
  },
  "OCB0088055": {
    "type": "OCB_BLOCK",
    "cx": 4765.7,
    "cy": 1578.3,
    "x1": 4690.0,
    "y1": 1564.4,
    "x2": 4841.4,
    "y2": 1592.3,
    "ports": [
      {
        "name": "FLAG",
        "type": "PORT",
        "cx": 4621.5,
        "cy": 1449.2
      },
      {
        "name": "NO",
        "type": "PORT",
        "cx": 4670.8,
        "cy": 1452.8
      },
      {
        "name": "YES",
        "type": "PORT",
        "cx": 4609.0,
        "cy": 1510.8
      },
      {
        "name": "T",
        "type": "BLOCK_TYPE",
        "cx": 4680.4,
        "cy": 1514.0
      },
      {
        "name": "OUT",
        "type": "PORT",
        "cx": 4670.8,
        "cy": 1584.2
      }
    ]
  },
  "D03-526-01": {
    "type": "REF_SIGNAL",
    "cx": 4079.0,
    "cy": 1588.3,
    "x1": 4013.0,
    "y1": 1574.4,
    "x2": 4145.0,
    "y2": 1602.3,
    "ports": [
      {
        "name": "3/526",
        "type": "SHEET_REF",
        "cx": 4004.4,
        "cy": 1632.5
      }
    ]
  },
  "OCB0088010": {
    "type": "OCB_BLOCK",
    "cx": 1045.7,
    "cy": 1598.3,
    "x1": 970.0,
    "y1": 1584.4,
    "x2": 1121.4,
    "y2": 1612.3,
    "ports": [
      {
        "name": "FLAG",
        "type": "PORT",
        "cx": 901.5,
        "cy": 1469.2
      },
      {
        "name": "NO",
        "type": "PORT",
        "cx": 950.8,
        "cy": 1472.8
      },
      {
        "name": "YES",
        "type": "PORT",
        "cx": 889.0,
        "cy": 1530.8
      },
      {
        "name": "T",
        "type": "BLOCK_TYPE",
        "cx": 960.4,
        "cy": 1534.0
      },
      {
        "name": "OUT",
        "type": "PORT",
        "cx": 950.8,
        "cy": 1604.2
      }
    ]
  },
  "OCB008801D": {
    "type": "OCB_BLOCK",
    "cx": 2067.8,
    "cy": 1598.3,
    "x1": 1990.0,
    "y1": 1584.4,
    "x2": 2145.6,
    "y2": 1612.3,
    "ports": [
      {
        "name": "FLAG",
        "type": "PORT",
        "cx": 1921.5,
        "cy": 1469.2
      },
      {
        "name": "NO",
        "type": "PORT",
        "cx": 1970.8,
        "cy": 1472.8
      },
      {
        "name": "YES",
        "type": "PORT",
        "cx": 1909.0,
        "cy": 1530.8
      },
      {
        "name": "T",
        "type": "BLOCK_TYPE",
        "cx": 1980.4,
        "cy": 1534.0
      },
      {
        "name": "OUT",
        "type": "PORT",
        "cx": 1970.8,
        "cy": 1604.2
      }
    ]
  },
  "OCB0088031": {
    "type": "OCB_BLOCK",
    "cx": 3425.7,
    "cy": 1598.3,
    "x1": 3350.0,
    "y1": 1584.4,
    "x2": 3501.4,
    "y2": 1612.3,
    "ports": [
      {
        "name": "FLAG",
        "type": "PORT",
        "cx": 3281.5,
        "cy": 1469.2
      },
      {
        "name": "NO",
        "type": "PORT",
        "cx": 3330.8,
        "cy": 1472.8
      },
      {
        "name": "YES",
        "type": "PORT",
        "cx": 3269.0,
        "cy": 1530.8
      },
      {
        "name": "T",
        "type": "BLOCK_TYPE",
        "cx": 3340.4,
        "cy": 1534.0
      },
      {
        "name": "OUT",
        "type": "PORT",
        "cx": 3330.8,
        "cy": 1604.2
      }
    ]
  },
  "SIT2681A": {
    "type": "SIGNAL",
    "cx": 576.5,
    "cy": 1620.3,
    "x1": 521.0,
    "y1": 1606.4,
    "x2": 632.1,
    "y2": 1634.3,
    "ports": [
      {
        "name": "A",
        "type": "PORT",
        "cx": 560.4,
        "cy": 1658.2
      },
      {
        "name": "G",
        "type": "PORT",
        "cx": 600.1,
        "cy": 1658.2
      }
    ]
  },
  "SIT2681B": {
    "type": "SIGNAL",
    "cx": 1676.5,
    "cy": 1620.3,
    "x1": 1621.0,
    "y1": 1606.4,
    "x2": 1732.1,
    "y2": 1634.3,
    "ports": [
      {
        "name": "A",
        "type": "PORT",
        "cx": 1660.4,
        "cy": 1658.2
      },
      {
        "name": "G",
        "type": "PORT",
        "cx": 1700.1,
        "cy": 1658.2
      }
    ]
  },
  "SIT2681C": {
    "type": "SIGNAL",
    "cx": 2976.2,
    "cy": 1620.3,
    "x1": 2920.0,
    "y1": 1606.4,
    "x2": 3032.5,
    "y2": 1634.3,
    "ports": [
      {
        "name": "A",
        "type": "PORT",
        "cx": 2960.4,
        "cy": 1658.2
      },
      {
        "name": "G",
        "type": "PORT",
        "cx": 3000.1,
        "cy": 1658.2
      }
    ]
  },
  "SIT2681D": {
    "type": "SIGNAL",
    "cx": 4236.2,
    "cy": 1740.3,
    "x1": 4180.0,
    "y1": 1726.4,
    "x2": 4292.5,
    "y2": 1754.3,
    "ports": [
      {
        "name": "A",
        "type": "PORT",
        "cx": 4220.4,
        "cy": 1778.2
      },
      {
        "name": "G",
        "type": "PORT",
        "cx": 4260.1,
        "cy": 1778.2
      }
    ]
  },
  "ALG-0113011": {
    "type": "ALG_BLOCK",
    "cx": 251.8,
    "cy": 1775.3,
    "x1": 174.0,
    "y1": 1761.4,
    "x2": 329.6,
    "y2": 1789.3,
    "ports": [
      {
        "name": "A",
        "type": "PORT",
        "cx": 339.5,
        "cy": 1672.0
      },
      {
        "name": "OUT",
        "type": "PORT",
        "cx": 330.8,
        "cy": 1744.2
      }
    ]
  },
  "ALG-0113033": {
    "type": "ALG_BLOCK",
    "cx": 2651.8,
    "cy": 1775.3,
    "x1": 2574.0,
    "y1": 1761.4,
    "x2": 2729.6,
    "y2": 1789.3,
    "ports": [
      {
        "name": "A",
        "type": "PORT",
        "cx": 2739.5,
        "cy": 1672.0
      },
      {
        "name": "OUT",
        "type": "PORT",
        "cx": 2730.8,
        "cy": 1744.2
      }
    ]
  },
  "ALG-011305D": {
    "type": "ALG_BLOCK",
    "cx": 1413.9,
    "cy": 1795.3,
    "x1": 1334.0,
    "y1": 1781.4,
    "x2": 1493.8,
    "y2": 1809.3,
    "ports": [
      {
        "name": "A",
        "type": "PORT",
        "cx": 1499.5,
        "cy": 1692.0
      },
      {
        "name": "OUT",
        "type": "PORT",
        "cx": 1490.8,
        "cy": 1764.2
      }
    ]
  },
  "OCB0088046": {
    "type": "OCB_BLOCK",
    "cx": 4765.7,
    "cy": 1858.3,
    "x1": 4690.0,
    "y1": 1844.4,
    "x2": 4841.4,
    "y2": 1872.3,
    "ports": [
      {
        "name": "FLAG",
        "type": "PORT",
        "cx": 4621.5,
        "cy": 1729.2
      },
      {
        "name": "NO",
        "type": "PORT",
        "cx": 4670.8,
        "cy": 1732.8
      },
      {
        "name": "YES",
        "type": "PORT",
        "cx": 4609.0,
        "cy": 1790.8
      },
      {
        "name": "T",
        "type": "BLOCK_TYPE",
        "cx": 4680.4,
        "cy": 1794.0
      },
      {
        "name": "OUT",
        "type": "PORT",
        "cx": 4670.8,
        "cy": 1864.2
      },
      {
        "name": "STPT",
        "type": "PORT",
        "cx": 4670.8,
        "cy": 1984.9
      }
    ]
  },
  "OCB0088002": {
    "type": "OCB_BLOCK",
    "cx": 1045.7,
    "cy": 1898.3,
    "x1": 970.0,
    "y1": 1884.4,
    "x2": 1121.4,
    "y2": 1912.3,
    "ports": [
      {
        "name": "FLAG",
        "type": "PORT",
        "cx": 901.5,
        "cy": 1769.2
      },
      {
        "name": "NO",
        "type": "PORT",
        "cx": 950.8,
        "cy": 1772.8
      },
      {
        "name": "YES",
        "type": "PORT",
        "cx": 889.0,
        "cy": 1830.8
      },
      {
        "name": "T",
        "type": "BLOCK_TYPE",
        "cx": 960.4,
        "cy": 1834.0
      },
      {
        "name": "OUT",
        "type": "PORT",
        "cx": 950.8,
        "cy": 1904.2
      },
      {
        "name": "STPT",
        "type": "PORT",
        "cx": 950.8,
        "cy": 1984.9
      }
    ]
  },
  "OCB008805E": {
    "type": "OCB_BLOCK",
    "cx": 2067.1,
    "cy": 1898.3,
    "x1": 1990.0,
    "y1": 1884.4,
    "x2": 2144.2,
    "y2": 1912.3,
    "ports": [
      {
        "name": "FLAG",
        "type": "PORT",
        "cx": 1921.5,
        "cy": 1769.2
      },
      {
        "name": "NO",
        "type": "PORT",
        "cx": 1970.8,
        "cy": 1772.8
      },
      {
        "name": "YES",
        "type": "PORT",
        "cx": 1909.0,
        "cy": 1830.8
      },
      {
        "name": "T",
        "type": "BLOCK_TYPE",
        "cx": 1980.4,
        "cy": 1834.0
      },
      {
        "name": "OUT",
        "type": "PORT",
        "cx": 1970.8,
        "cy": 1904.2
      },
      {
        "name": "STPT",
        "type": "PORT",
        "cx": 1970.8,
        "cy": 1984.9
      }
    ]
  },
  "OCB008802F": {
    "type": "OCB_BLOCK",
    "cx": 3426.4,
    "cy": 1898.3,
    "x1": 3350.0,
    "y1": 1884.4,
    "x2": 3502.8,
    "y2": 1912.3,
    "ports": [
      {
        "name": "FLAG",
        "type": "PORT",
        "cx": 3281.5,
        "cy": 1769.2
      },
      {
        "name": "NO",
        "type": "PORT",
        "cx": 3330.8,
        "cy": 1772.8
      },
      {
        "name": "YES",
        "type": "PORT",
        "cx": 3269.0,
        "cy": 1830.8
      },
      {
        "name": "T",
        "type": "BLOCK_TYPE",
        "cx": 3340.4,
        "cy": 1834.0
      },
      {
        "name": "OUT",
        "type": "PORT",
        "cx": 3330.8,
        "cy": 1904.2
      },
      {
        "name": "STPT",
        "type": "PORT",
        "cx": 3330.8,
        "cy": 1984.9
      }
    ]
  },
  "D03-511-06": {
    "type": "REF_SIGNAL",
    "cx": 1619.0,
    "cy": 1948.3,
    "x1": 1553.0,
    "y1": 1934.4,
    "x2": 1685.0,
    "y2": 1962.3,
    "ports": [
      {
        "name": "3/511",
        "type": "SHEET_REF",
        "cx": 1544.4,
        "cy": 1992.5
      }
    ]
  },
  "D03-511-03": {
    "type": "REF_SIGNAL",
    "cx": 499.0,
    "cy": 1988.3,
    "x1": 433.0,
    "y1": 1974.4,
    "x2": 565.0,
    "y2": 2002.3,
    "ports": [
      {
        "name": "3/511",
        "type": "SHEET_REF",
        "cx": 424.4,
        "cy": 2032.5
      }
    ]
  },
  "D03-511-09": {
    "type": "REF_SIGNAL",
    "cx": 2859.0,
    "cy": 1988.3,
    "x1": 2793.0,
    "y1": 1974.4,
    "x2": 2925.0,
    "y2": 2002.3,
    "ports": [
      {
        "name": "3/511",
        "type": "SHEET_REF",
        "cx": 2784.4,
        "cy": 2032.5
      }
    ]
  },
  "D03-511-04": {
    "type": "REF_SIGNAL",
    "cx": 1619.0,
    "cy": 2048.3,
    "x1": 1553.0,
    "y1": 2034.4,
    "x2": 1685.0,
    "y2": 2062.3,
    "ports": [
      {
        "name": "3/511",
        "type": "SHEET_REF",
        "cx": 1544.4,
        "cy": 2092.5
      }
    ]
  },
  "D03-511-05": {
    "type": "REF_SIGNAL",
    "cx": 1619.0,
    "cy": 2148.3,
    "x1": 1553.0,
    "y1": 2134.4,
    "x2": 1685.0,
    "y2": 2162.3,
    "ports": [
      {
        "name": "3/511",
        "type": "SHEET_REF",
        "cx": 1544.4,
        "cy": 2192.5
      }
    ]
  },
  "OCB008800E": {
    "type": "OCB_BLOCK",
    "cx": 1027.1,
    "cy": 2165.3,
    "x1": 950.0,
    "y1": 2151.4,
    "x2": 1104.2,
    "y2": 2179.3,
    "ports": [
      {
        "name": "K",
        "type": "BLOCK_TYPE",
        "cx": 906.3,
        "cy": 2103.3
      },
      {
        "name": "OUT",
        "type": "PORT",
        "cx": 930.8,
        "cy": 2164.2
      }
    ]
  },
  "OCB008801E": {
    "type": "OCB_BLOCK",
    "cx": 2047.1,
    "cy": 2165.3,
    "x1": 1970.0,
    "y1": 2151.4,
    "x2": 2124.2,
    "y2": 2179.3,
    "ports": [
      {
        "name": "K",
        "type": "BLOCK_TYPE",
        "cx": 1926.3,
        "cy": 2103.3
      },
      {
        "name": "OUT",
        "type": "PORT",
        "cx": 1950.8,
        "cy": 2164.2
      }
    ]
  },
  "OCB0088032": {
    "type": "OCB_BLOCK",
    "cx": 3405.7,
    "cy": 2165.3,
    "x1": 3330.0,
    "y1": 2151.4,
    "x2": 3481.4,
    "y2": 2179.3,
    "ports": [
      {
        "name": "K",
        "type": "BLOCK_TYPE",
        "cx": 3286.3,
        "cy": 2103.3
      },
      {
        "name": "OUT",
        "type": "PORT",
        "cx": 3310.8,
        "cy": 2164.2
      }
    ]
  },
  "OCB0088047": {
    "type": "OCB_BLOCK",
    "cx": 4745.7,
    "cy": 2165.3,
    "x1": 4670.0,
    "y1": 2151.4,
    "x2": 4821.4,
    "y2": 2179.3,
    "ports": [
      {
        "name": "K",
        "type": "BLOCK_TYPE",
        "cx": 4626.3,
        "cy": 2103.3
      },
      {
        "name": "OUT",
        "type": "PORT",
        "cx": 4779.8,
        "cy": 2230.8
      }
    ]
  },
  "D03-511-01": {
    "type": "REF_SIGNAL",
    "cx": 499.0,
    "cy": 2188.3,
    "x1": 433.0,
    "y1": 2174.4,
    "x2": 565.0,
    "y2": 2202.3,
    "ports": [
      {
        "name": "3/511",
        "type": "SHEET_REF",
        "cx": 424.4,
        "cy": 2232.5
      }
    ]
  },
  "D03-511-07": {
    "type": "REF_SIGNAL",
    "cx": 2859.0,
    "cy": 2188.3,
    "x1": 2793.0,
    "y1": 2174.4,
    "x2": 2925.0,
    "y2": 2202.3,
    "ports": [
      {
        "name": "3/511",
        "type": "SHEET_REF",
        "cx": 2784.4,
        "cy": 2232.5
      }
    ]
  },
  "D03-511-10": {
    "type": "REF_SIGNAL",
    "cx": 4199.0,
    "cy": 2208.3,
    "x1": 4133.0,
    "y1": 2194.4,
    "x2": 4265.0,
    "y2": 2222.3,
    "ports": [
      {
        "name": "3/511",
        "type": "SHEET_REF",
        "cx": 4124.4,
        "cy": 2252.5
      }
    ]
  },
  "D03-511-02": {
    "type": "REF_SIGNAL",
    "cx": 499.0,
    "cy": 2308.3,
    "x1": 433.0,
    "y1": 2294.4,
    "x2": 565.0,
    "y2": 2322.3,
    "ports": [
      {
        "name": "3/511",
        "type": "SHEET_REF",
        "cx": 424.4,
        "cy": 2352.5
      }
    ]
  },
  "D03-511-08": {
    "type": "REF_SIGNAL",
    "cx": 2859.0,
    "cy": 2308.3,
    "x1": 2793.0,
    "y1": 2294.4,
    "x2": 2925.0,
    "y2": 2322.3,
    "ports": [
      {
        "name": "3/511",
        "type": "SHEET_REF",
        "cx": 2784.4,
        "cy": 2352.5
      }
    ]
  },
  "D03-511-11": {
    "type": "REF_SIGNAL",
    "cx": 4199.0,
    "cy": 2308.3,
    "x1": 4133.0,
    "y1": 2294.4,
    "x2": 4265.0,
    "y2": 2322.3,
    "ports": [
      {
        "name": "3/511",
        "type": "SHEET_REF",
        "cx": 4124.4,
        "cy": 2352.5
      }
    ]
  },
  "ALG-011300C": {
    "type": "ALG_BLOCK",
    "cx": 1029.9,
    "cy": 2580.3,
    "x1": 950.0,
    "y1": 2566.4,
    "x2": 1109.8,
    "y2": 2594.3,
    "ports": [
      {
        "name": "OUT",
        "type": "PORT",
        "cx": 930.8,
        "cy": 2544.2
      },
      {
        "name": "FLAG",
        "type": "PORT",
        "cx": 881.5,
        "cy": 2689.2
      },
      {
        "name": "NO",
        "type": "PORT",
        "cx": 930.8,
        "cy": 2692.8
      }
    ]
  },
  "ALG-0113020": {
    "type": "ALG_BLOCK",
    "cx": 2047.8,
    "cy": 2580.3,
    "x1": 1970.0,
    "y1": 2566.4,
    "x2": 2125.6,
    "y2": 2594.3,
    "ports": [
      {
        "name": "OUT",
        "type": "PORT",
        "cx": 1950.8,
        "cy": 2544.2
      },
      {
        "name": "FLAG",
        "type": "PORT",
        "cx": 1901.5,
        "cy": 2689.2
      },
      {
        "name": "NO",
        "type": "PORT",
        "cx": 1950.8,
        "cy": 2692.8
      }
    ]
  },
  "ALG-0113034": {
    "type": "ALG_BLOCK",
    "cx": 3407.8,
    "cy": 2580.3,
    "x1": 3330.0,
    "y1": 2566.4,
    "x2": 3485.6,
    "y2": 2594.3,
    "ports": [
      {
        "name": "OUT",
        "type": "PORT",
        "cx": 3310.8,
        "cy": 2544.2
      },
      {
        "name": "FLAG",
        "type": "PORT",
        "cx": 3261.5,
        "cy": 2689.2
      },
      {
        "name": "NO",
        "type": "PORT",
        "cx": 3310.8,
        "cy": 2692.8
      }
    ]
  },
  "ALG-0113049": {
    "type": "ALG_BLOCK",
    "cx": 4747.8,
    "cy": 2580.3,
    "x1": 4670.0,
    "y1": 2566.4,
    "x2": 4825.6,
    "y2": 2594.3,
    "ports": [
      {
        "name": "OUT",
        "type": "PORT",
        "cx": 4650.8,
        "cy": 2544.2
      },
      {
        "name": "FLAG",
        "type": "PORT",
        "cx": 4601.5,
        "cy": 2689.2
      },
      {
        "name": "NO",
        "type": "PORT",
        "cx": 4650.8,
        "cy": 2692.8
      }
    ]
  },
  "D03-024-01": {
    "type": "REF_SIGNAL",
    "cx": 639.0,
    "cy": 2628.3,
    "x1": 573.0,
    "y1": 2614.4,
    "x2": 705.0,
    "y2": 2642.3,
    "ports": [
      {
        "name": "3/024",
        "type": "SHEET_REF",
        "cx": 564.4,
        "cy": 2672.5
      }
    ]
  },
  "D03-030-01": {
    "type": "REF_SIGNAL",
    "cx": 1699.0,
    "cy": 2628.3,
    "x1": 1633.0,
    "y1": 2614.4,
    "x2": 1765.0,
    "y2": 2642.3,
    "ports": [
      {
        "name": "3/030",
        "type": "SHEET_REF",
        "cx": 1624.4,
        "cy": 2672.5
      }
    ]
  },
  "D03-036-01": {
    "type": "REF_SIGNAL",
    "cx": 2719.0,
    "cy": 2628.3,
    "x1": 2653.0,
    "y1": 2614.4,
    "x2": 2785.0,
    "y2": 2642.3,
    "ports": [
      {
        "name": "3/036",
        "type": "SHEET_REF",
        "cx": 2644.4,
        "cy": 2672.5
      }
    ]
  },
  "D03-042-01": {
    "type": "REF_SIGNAL",
    "cx": 4419.0,
    "cy": 2628.3,
    "x1": 4353.0,
    "y1": 2614.4,
    "x2": 4485.0,
    "y2": 2642.3,
    "ports": [
      {
        "name": "3/042",
        "type": "SHEET_REF",
        "cx": 4344.4,
        "cy": 2672.5
      }
    ]
  },
  "OCB0088012": {
    "type": "OCB_BLOCK",
    "cx": 625.7,
    "cy": 2790.3,
    "x1": 550.0,
    "y1": 2776.4,
    "x2": 701.4,
    "y2": 2804.3,
    "ports": [
      {
        "name": "A",
        "type": "PORT",
        "cx": 499.6,
        "cy": 2745.7
      },
      {
        "name": "OUT",
        "type": "PORT",
        "cx": 559.8,
        "cy": 2750.8
      }
    ]
  },
  "OCB0088023": {
    "type": "OCB_BLOCK",
    "cx": 1665.7,
    "cy": 2790.3,
    "x1": 1590.0,
    "y1": 2776.4,
    "x2": 1741.4,
    "y2": 2804.3,
    "ports": [
      {
        "name": "A",
        "type": "PORT",
        "cx": 1539.7,
        "cy": 2745.7
      },
      {
        "name": "OUT",
        "type": "PORT",
        "cx": 1599.8,
        "cy": 2750.8
      }
    ]
  },
  "OCB0088036": {
    "type": "OCB_BLOCK",
    "cx": 2685.7,
    "cy": 2790.3,
    "x1": 2610.0,
    "y1": 2776.4,
    "x2": 2761.4,
    "y2": 2804.3,
    "ports": [
      {
        "name": "A",
        "type": "PORT",
        "cx": 2559.7,
        "cy": 2745.7
      },
      {
        "name": "OUT",
        "type": "PORT",
        "cx": 2619.8,
        "cy": 2750.8
      }
    ]
  },
  "OCB008804C": {
    "type": "OCB_BLOCK",
    "cx": 4387.8,
    "cy": 2790.3,
    "x1": 4310.0,
    "y1": 2776.4,
    "x2": 4465.6,
    "y2": 2804.3,
    "ports": [
      {
        "name": "A",
        "type": "PORT",
        "cx": 4259.6,
        "cy": 2745.7
      },
      {
        "name": "OUT",
        "type": "PORT",
        "cx": 4319.8,
        "cy": 2750.8
      }
    ]
  },
  "OCB008800F": {
    "type": "OCB_BLOCK",
    "cx": 1026.4,
    "cy": 2818.3,
    "x1": 950.0,
    "y1": 2804.4,
    "x2": 1102.8,
    "y2": 2832.3,
    "ports": [
      {
        "name": "YES",
        "type": "PORT",
        "cx": 869.0,
        "cy": 2750.8
      },
      {
        "name": "T",
        "type": "BLOCK_TYPE",
        "cx": 940.4,
        "cy": 2754.0
      },
      {
        "name": "OUT",
        "type": "PORT",
        "cx": 930.8,
        "cy": 2824.2
      }
    ]
  },
  "OCB0088021": {
    "type": "OCB_BLOCK",
    "cx": 2045.7,
    "cy": 2818.3,
    "x1": 1970.0,
    "y1": 2804.4,
    "x2": 2121.4,
    "y2": 2832.3,
    "ports": [
      {
        "name": "YES",
        "type": "PORT",
        "cx": 1889.0,
        "cy": 2750.8
      },
      {
        "name": "T",
        "type": "BLOCK_TYPE",
        "cx": 1960.4,
        "cy": 2754.0
      },
      {
        "name": "OUT",
        "type": "PORT",
        "cx": 1950.8,
        "cy": 2824.2
      }
    ]
  },
  "OCB0088035": {
    "type": "OCB_BLOCK",
    "cx": 3405.7,
    "cy": 2818.3,
    "x1": 3330.0,
    "y1": 2804.4,
    "x2": 3481.4,
    "y2": 2832.3,
    "ports": [
      {
        "name": "YES",
        "type": "PORT",
        "cx": 3249.0,
        "cy": 2750.8
      },
      {
        "name": "T",
        "type": "BLOCK_TYPE",
        "cx": 3320.4,
        "cy": 2754.0
      },
      {
        "name": "OUT",
        "type": "PORT",
        "cx": 3310.8,
        "cy": 2824.2
      }
    ]
  },
  "OCB008804A": {
    "type": "OCB_BLOCK",
    "cx": 4747.1,
    "cy": 2818.3,
    "x1": 4670.0,
    "y1": 2804.4,
    "x2": 4824.2,
    "y2": 2832.3,
    "ports": [
      {
        "name": "YES",
        "type": "PORT",
        "cx": 4589.0,
        "cy": 2750.8
      },
      {
        "name": "T",
        "type": "BLOCK_TYPE",
        "cx": 4660.4,
        "cy": 2754.0
      },
      {
        "name": "OUT",
        "type": "PORT",
        "cx": 4650.8,
        "cy": 2824.2
      }
    ]
  },
  "OCB0088013": {
    "type": "OCB_BLOCK",
    "cx": 1025.7,
    "cy": 2940.3,
    "x1": 950.0,
    "y1": 2926.4,
    "x2": 1101.4,
    "y2": 2954.3,
    "ports": []
  },
  "OCB0088022": {
    "type": "OCB_BLOCK",
    "cx": 2045.7,
    "cy": 2940.3,
    "x1": 1970.0,
    "y1": 2926.4,
    "x2": 2121.4,
    "y2": 2954.3,
    "ports": []
  },
  "OCB0088038": {
    "type": "OCB_BLOCK",
    "cx": 3405.7,
    "cy": 2940.3,
    "x1": 3330.0,
    "y1": 2926.4,
    "x2": 3481.4,
    "y2": 2954.3,
    "ports": []
  },
  "OCB008804D": {
    "type": "OCB_BLOCK",
    "cx": 4747.8,
    "cy": 2940.3,
    "x1": 4670.0,
    "y1": 2926.4,
    "x2": 4825.6,
    "y2": 2954.3,
    "ports": []
  },
  "SIC2681B": {
    "type": "SIGNAL",
    "cx": 1936.9,
    "cy": 3031.3,
    "x1": 1880.0,
    "y1": 3017.4,
    "x2": 1993.9,
    "y2": 3045.3,
    "ports": []
  },
  "SIC2681A": {
    "type": "SIGNAL",
    "cx": 916.9,
    "cy": 3051.3,
    "x1": 860.0,
    "y1": 3037.4,
    "x2": 973.9,
    "y2": 3065.3,
    "ports": []
  },
  "SIC2681C": {
    "type": "SIGNAL",
    "cx": 3297.6,
    "cy": 3051.3,
    "x1": 3240.0,
    "y1": 3037.4,
    "x2": 3355.3,
    "y2": 3065.3,
    "ports": []
  },
  "SIC2681D": {
    "type": "SIGNAL",
    "cx": 4655.6,
    "cy": 3051.3,
    "x1": 4598.0,
    "y1": 3037.4,
    "x2": 4713.3,
    "y2": 3065.3,
    "ports": []
  }
}